qicd.py
qibuild/__init__.py
qibuild/breakpad.py
qibuild/build.py
qibuild/build_config.py
qibuild/cmake_builder.py
qibuild/config.py
qibuild/deploy.py
qibuild/deps.py
qibuild/dlls.py
qibuild/dylibs.py
qibuild/find.py
qibuild/gcov.py
qibuild/gdb.py
qibuild/parallel_builder.py
qibuild/parsers.py
qibuild/profile.py
qibuild/project.py
qibuild/run.py
qibuild/solibs.py
qibuild/test_runner.py
qibuild/wizard.py
qibuild/worktree.py
qibuild/actions/__init__.py
qibuild/actions/add_config.py
qibuild/actions/clean.py
qibuild/actions/config.py
qibuild/actions/configure.py
qibuild/actions/convert.py
qibuild/actions/depends.py
qibuild/actions/deploy.py
qibuild/actions/find.py
qibuild/actions/foreach.py
qibuild/actions/gen_cmake_module.py
qibuild/actions/get_licenses.py
qibuild/actions/info.py
qibuild/actions/init.py
qibuild/actions/install.py
qibuild/actions/list.py
qibuild/actions/list_binaries.py
qibuild/actions/list_configs.py
qibuild/actions/list_profiles.py
qibuild/actions/make.py
qibuild/actions/make_host_tools.py
qibuild/actions/open.py
qibuild/actions/package.py
qibuild/actions/rm_config.py
qibuild/actions/run.py
qibuild/actions/set_default.py
qibuild/actions/set_host_config.py
qibuild/actions/sourceme.py
qibuild/actions/status.py
qibuild/actions/test.py
qibuild/cmake/__init__.py
qibuild/cmake/modules.py
qibuild/cmake/profiling.py
qibuild/test/__init__.py
qibuild/test/conftest.py
qibuild/test/test_breakpad.py
qibuild/test/test_build_config.py
qibuild/test/test_build_worktree.py
qibuild/test/test_cmake.py
qibuild/test/test_cmake_builder.py
qibuild/test/test_cmake_modules.py
qibuild/test/test_cmake_profiling.py
qibuild/test/test_config.py
qibuild/test/test_coverage.py
qibuild/test/test_deps.py
qibuild/test/test_dylibs.py
qibuild/test/test_find.py
qibuild/test/test_fixture.py
qibuild/test/test_gdb.py
qibuild/test/test_install.py
qibuild/test/test_open.py
qibuild/test/test_parallel_builder.py
qibuild/test/test_parser.py
qibuild/test/test_perf.py
qibuild/test/test_profile.py
qibuild-3.18.dist-info/AUTHORS
qibuild-3.18.dist-info/COPYING
qibuild-3.18.dist-info/METADATA
qibuild-3.18.dist-info/WHEEL
qibuild-3.18.dist-info/entry_points.txt
qibuild-3.18.dist-info/top_level.txt
qibuild-3.18.dist-info/RECORD
